mailtmpy/__init__.py
mailtmpy/email.py
mailtmpy/helpers.py
mailtmpy/listen.py
mailtmpy/models.py
mailtmpy-0.1.4.dist-info/LICENSE
mailtmpy-0.1.4.dist-info/METADATA
mailtmpy-0.1.4.dist-info/WHEEL
mailtmpy-0.1.4.dist-info/RECORD
